<?xml version="1.0" ?>
<e107HelperForm version="1.0">

   <form name="e107helpers_developer_admin_prefs_35_form" type="HELPER_FORM_TYPE_E107_PREF">
      <batchcount name="yell_upload_repeats" class="tbox"/>

      <checkbox name="yell_name_pref" label="YELL_LAN_ENTRY_01_0" class="tbox">
         <default var="e107pref">0</default>
         <value>1</value>
      </checkbox>

      <checkbox name="yell_description_pref" label="YELL_LAN_ENTRY_02_0" class="tbox">
         <default var="e107pref">0</default>
         <value>1</value>
      </checkbox>

      <checkbox name="yell_contact_name_pref" label="YELL_LAN_ENTRY_03_0" class="tbox">
         <default var="e107pref">0</default>
         <value>1</value>
      </checkbox>

      <checkbox name="yell_tel1_pref" label="YELL_LAN_ENTRY_04_0" class="tbox">
         <default var="e107pref">0</default>
         <value>1</value>
      </checkbox>

      <checkbox name="yell_tel2_pref" label="YELL_LAN_ENTRY_05_0" class="tbox">
         <default var="e107pref">0</default>
         <value>1</value>
      </checkbox>

      <checkbox name="yell_email_pref" label="YELL_LAN_ENTRY_06_0" class="tbox">
         <default var="e107pref">0</default>
         <value>1</value>
      </checkbox>

      <checkbox name="yell_website_pref" label="YELL_LAN_ENTRY_07_0" class="tbox">
         <default var="e107pref">0</default>
         <value>1</value>
      </checkbox>

      <checkbox name="yell_image_pref" label="YELL_LAN_ENTRY_08_0" class="tbox">
         <default var="e107pref">0</default>
         <value>1</value>
      </checkbox>

      <checkbox name="yell_category_pref" label="YELL_LAN_ENTRY_09_0" class="tbox">
         <default var="e107pref">0</default>
         <value>1</value>
      </checkbox>

      <checkbox name="yell_approved_pref" label="YELL_LAN_ENTRY_10_0" class="tbox">
         <default var="e107pref">0</default>
         <value>1</value>
      </checkbox>

      <checkbox name="yell_submitter_pref" label="YELL_LAN_ENTRY_11_0" class="tbox">
         <default var="e107pref">0</default>
         <value>1</value>
      </checkbox>

   </form>

</e107HelperForm>